ShujujiegouSiweiZhongwenban/README.md
ShujujiegouSiweiZhongwenban/__init__.py
ShujujiegouSiweiZhongwenban/__main__.py
ShujujiegouSiweiZhongwenban/file.epub
ShujujiegouSiweiZhongwenban/index.html
ShujujiegouSiweiZhongwenban/css/__init__.py
ShujujiegouSiweiZhongwenban/css/annotations.css
ShujujiegouSiweiZhongwenban/css/main.css
ShujujiegouSiweiZhongwenban/css/normalize.css
ShujujiegouSiweiZhongwenban/css/popup.css
ShujujiegouSiweiZhongwenban/font/__init__.py
ShujujiegouSiweiZhongwenban/font/fontello.eot
ShujujiegouSiweiZhongwenban/font/fontello.svg
ShujujiegouSiweiZhongwenban/font/fontello.ttf
ShujujiegouSiweiZhongwenban/font/fontello.woff
ShujujiegouSiweiZhongwenban/img/__init__.py
ShujujiegouSiweiZhongwenban/img/annotator-glyph-sprite.png
ShujujiegouSiweiZhongwenban/img/annotator-icon-sprite.png
ShujujiegouSiweiZhongwenban/img/apple-touch-icon.png
ShujujiegouSiweiZhongwenban/img/cancelfullscreen.png
ShujujiegouSiweiZhongwenban/img/close.png
ShujujiegouSiweiZhongwenban/img/fullscreen.png
ShujujiegouSiweiZhongwenban/img/loader.gif
ShujujiegouSiweiZhongwenban/img/menu-icon.png
ShujujiegouSiweiZhongwenban/img/save.png
ShujujiegouSiweiZhongwenban/img/saved.png
ShujujiegouSiweiZhongwenban/img/settings-s.png
ShujujiegouSiweiZhongwenban/img/settings.png
ShujujiegouSiweiZhongwenban/img/star.png
ShujujiegouSiweiZhongwenban/js/__init__.py
ShujujiegouSiweiZhongwenban/js/epub.js
ShujujiegouSiweiZhongwenban/js/epub.min.js
ShujujiegouSiweiZhongwenban/js/epub.min.map
ShujujiegouSiweiZhongwenban/js/hooks.min.js
ShujujiegouSiweiZhongwenban/js/hooks.min.map
ShujujiegouSiweiZhongwenban/js/reader.js
ShujujiegouSiweiZhongwenban/js/reader.js.map
ShujujiegouSiweiZhongwenban/js/reader.min.js
ShujujiegouSiweiZhongwenban/js/reader.min.map
ShujujiegouSiweiZhongwenban/js/hooks/__init__.py
ShujujiegouSiweiZhongwenban/js/hooks/extensions/__init__.py
ShujujiegouSiweiZhongwenban/js/hooks/extensions/highlight.js
ShujujiegouSiweiZhongwenban/js/libs/__init__.py
shujujiegou_siwei_zhongwenban-2024.3.2.0.dist-info/METADATA
shujujiegou_siwei_zhongwenban-2024.3.2.0.dist-info/WHEEL
shujujiegou_siwei_zhongwenban-2024.3.2.0.dist-info/entry_points.txt
shujujiegou_siwei_zhongwenban-2024.3.2.0.dist-info/top_level.txt
shujujiegou_siwei_zhongwenban-2024.3.2.0.dist-info/RECORD
